[
    {
        "hero_name": "lina",
        "votes": 59946,
        "image_url": "https:\/\/cdn.akamai.steamstatic.com\/apps\/dota2\/images\/dota_react\/heroes\/lina.png"
    },
    {
        "hero_name": "dawnbreaker",
        "votes": 77820,
        "image_url": "https:\/\/cdn.akamai.steamstatic.com\/apps\/dota2\/images\/dota_react\/heroes\/dawnbreaker.png"
    },
    {
        "hero_name": "sniper",
        "votes": 220667,
        "image_url": "https:\/\/cdn.akamai.steamstatic.com\/apps\/dota2\/images\/dota_react\/heroes\/sniper.png"
    },
    {
        "hero_name": "sven",
        "votes": 10961,
        "image_url": "https:\/\/cdn.akamai.steamstatic.com\/apps\/dota2\/images\/dota_react\/heroes\/sven.png"
    },
    {
        "hero_name": "mirana",
        "votes": 46356,
        "image_url": "https:\/\/cdn.akamai.steamstatic.com\/apps\/dota2\/images\/dota_react\/heroes\/mirana.png"
    },
    {
        "hero_name": "life_stealer",
        "votes": 44689,
        "image_url": "https:\/\/cdn.akamai.steamstatic.com\/apps\/dota2\/images\/dota_react\/heroes\/life_stealer.png"
    },
    {
        "hero_name": "leshrac",
        "votes": 4923,
        "image_url": "https:\/\/cdn.akamai.steamstatic.com\/apps\/dota2\/images\/dota_react\/heroes\/leshrac.png"
    },
    {
        "hero_name": "queenofpain",
        "votes": 10213,
        "image_url": "https:\/\/cdn.akamai.steamstatic.com\/apps\/dota2\/images\/dota_react\/heroes\/queenofpain.png"
    },
    {
        "hero_name": "ringmaster",
        "votes": 16267,
        "image_url": "https:\/\/cdn.akamai.steamstatic.com\/apps\/dota2\/images\/dota_react\/heroes\/ringmaster.png"
    },
    {
        "hero_name": "templar_assassin",
        "votes": 16198,
        "image_url": "https:\/\/cdn.akamai.steamstatic.com\/apps\/dota2\/images\/dota_react\/heroes\/templar_assassin.png"
    },
    {
        "hero_name": "riki",
        "votes": 9577,
        "image_url": "https:\/\/cdn.akamai.steamstatic.com\/apps\/dota2\/images\/dota_react\/heroes\/riki.png"
    },
    {
        "hero_name": "magnataur",
        "votes": 10142,
        "image_url": "https:\/\/cdn.akamai.steamstatic.com\/apps\/dota2\/images\/dota_react\/heroes\/magnataur.png"
    },
    {
        "hero_name": "dark_willow",
        "votes": 16350,
        "image_url": "https:\/\/cdn.akamai.steamstatic.com\/apps\/dota2\/images\/dota_react\/heroes\/dark_willow.png"
    },
    {
        "hero_name": "mars",
        "votes": 2453,
        "image_url": "https:\/\/cdn.akamai.steamstatic.com\/apps\/dota2\/images\/dota_react\/heroes\/mars.png"
    }
]