[
    {
        "hero_name": "lina",
        "votes": 60123,
        "image_url": "https:\/\/cdn.akamai.steamstatic.com\/apps\/dota2\/images\/dota_react\/heroes\/lina.png"
    },
    {
        "hero_name": "dawnbreaker",
        "votes": 78075,
        "image_url": "https:\/\/cdn.akamai.steamstatic.com\/apps\/dota2\/images\/dota_react\/heroes\/dawnbreaker.png"
    },
    {
        "hero_name": "sniper",
        "votes": 223185,
        "image_url": "https:\/\/cdn.akamai.steamstatic.com\/apps\/dota2\/images\/dota_react\/heroes\/sniper.png"
    },
    {
        "hero_name": "sven",
        "votes": 10981,
        "image_url": "https:\/\/cdn.akamai.steamstatic.com\/apps\/dota2\/images\/dota_react\/heroes\/sven.png"
    },
    {
        "hero_name": "mirana",
        "votes": 46397,
        "image_url": "https:\/\/cdn.akamai.steamstatic.com\/apps\/dota2\/images\/dota_react\/heroes\/mirana.png"
    },
    {
        "hero_name": "life_stealer",
        "votes": 45570,
        "image_url": "https:\/\/cdn.akamai.steamstatic.com\/apps\/dota2\/images\/dota_react\/heroes\/life_stealer.png"
    },
    {
        "hero_name": "leshrac",
        "votes": 4952,
        "image_url": "https:\/\/cdn.akamai.steamstatic.com\/apps\/dota2\/images\/dota_react\/heroes\/leshrac.png"
    },
    {
        "hero_name": "queenofpain",
        "votes": 10289,
        "image_url": "https:\/\/cdn.akamai.steamstatic.com\/apps\/dota2\/images\/dota_react\/heroes\/queenofpain.png"
    },
    {
        "hero_name": "ringmaster",
        "votes": 16283,
        "image_url": "https:\/\/cdn.akamai.steamstatic.com\/apps\/dota2\/images\/dota_react\/heroes\/ringmaster.png"
    },
    {
        "hero_name": "templar_assassin",
        "votes": 16301,
        "image_url": "https:\/\/cdn.akamai.steamstatic.com\/apps\/dota2\/images\/dota_react\/heroes\/templar_assassin.png"
    },
    {
        "hero_name": "riki",
        "votes": 9707,
        "image_url": "https:\/\/cdn.akamai.steamstatic.com\/apps\/dota2\/images\/dota_react\/heroes\/riki.png"
    },
    {
        "hero_name": "magnataur",
        "votes": 10208,
        "image_url": "https:\/\/cdn.akamai.steamstatic.com\/apps\/dota2\/images\/dota_react\/heroes\/magnataur.png"
    },
    {
        "hero_name": "dark_willow",
        "votes": 16615,
        "image_url": "https:\/\/cdn.akamai.steamstatic.com\/apps\/dota2\/images\/dota_react\/heroes\/dark_willow.png"
    },
    {
        "hero_name": "mars",
        "votes": 2502,
        "image_url": "https:\/\/cdn.akamai.steamstatic.com\/apps\/dota2\/images\/dota_react\/heroes\/mars.png"
    }
]